flexiagent/__init__.py
flexiagent/builtin/__init__.py
flexiagent/builtin/agents/__init__.py
flexiagent/builtin/agents/agent_db_recognition.py
flexiagent/builtin/agents/agent_text2sql.py
flexiagent/builtin/agents/agent_text2sql_qa.py
flexiagent/builtin/agents/agent_text2sql_with_db_recog.py
flexiagent/builtin/function/__init__.py
flexiagent/builtin/function/http_call.py
flexiagent/config_keys.py
flexiagent/database/__init__.py
flexiagent/database/db_executor.py
flexiagent/indexer.py
flexiagent/llm/__init__.py
flexiagent/llm/config.py
flexiagent/llm/engine/__init__.py
flexiagent/llm/engine/engine_base.py
flexiagent/llm/engine/llama_cpp.py
flexiagent/llm/engine/openai.py
flexiagent/llm/engine_factory.py
flexiagent/llm/histroy_tracker.py
flexiagent/llm/llm.py
flexiagent/llm/structured_schema.py
flexiagent/main.py
flexiagent/model/__init__.py
flexiagent/prompts/__init__.py
flexiagent/prompts/prompt.py
flexiagent/task/__init__.py
flexiagent/task/action_loader.py
flexiagent/task/base.py
flexiagent/task/condition.py
flexiagent/task/task_agent.py
flexiagent/task/task_node.py
flexiagent-0.1.0a8.dist-info/LICENSE
flexiagent-0.1.0a8.dist-info/METADATA
flexiagent-0.1.0a8.dist-info/WHEEL
flexiagent-0.1.0a8.dist-info/RECORD
