Metadata-Version: 2.1
Name: flexiagent
Version: 0.1.0a8
Summary: FlexiAgent is an open-source framework for creating agents based on Directed Acyclic Graphs (DAGs), featuring a user-friendly interface, built-in practical agents, and high configurability for efficient task management and rapid deployment.
Home-page: https://github.com/dzhsurf/flexiagent
License: MIT
Author: Hiram Deng
Author-email: 72371329+dzhsurf@users.noreply.github.com
Requires-Python: >=3.8,<4
Classifier: Intended Audience :: Developers
Classifier: License :: OSI Approved :: MIT License
Classifier: Operating System :: MacOS
Classifier: Operating System :: Microsoft :: Windows
Classifier: Operating System :: OS Independent
Classifier: Operating System :: POSIX
Classifier: Operating System :: POSIX :: Linux
Classifier: Programming Language :: Python :: 3
Classifier: Programming Language :: Python :: 3.8
Classifier: Programming Language :: Python :: 3.9
Classifier: Programming Language :: Python :: 3.10
Classifier: Programming Language :: Python :: 3.11
Classifier: Programming Language :: Python :: 3.12
Classifier: Topic :: Software Development :: Libraries :: Python Modules
Classifier: Typing :: Typed
Requires-Dist: huggingface-hub (>=0.24.6,<0.25.0)
Requires-Dist: llama-cpp-python (>=0.3.0,<0.4.0)
Requires-Dist: openai (>=1.43.0,<2.0.0)
Requires-Dist: pydantic (>=2.9.0,<3.0.0)
Requires-Dist: sqlalchemy (>=2.0.34,<3.0.0)
Requires-Dist: sqlparse (>=0.5.1,<0.6.0)
Project-URL: Repository, https://github.com/dzhsurf/flexiagent
